collective.imagemaps-2.0a1-py3.11-nspkg.pth
collective/imagemaps/__init__.py
collective/imagemaps/configure.zcml
collective/imagemaps/interfaces.py
collective/imagemaps/permissions.zcml
collective/imagemaps/setuphandlers.py
collective/imagemaps/testing.py
collective/imagemaps/behaviors/__init__.py
collective/imagemaps/behaviors/configure.zcml
collective/imagemaps/behaviors/image_map.py
collective/imagemaps/browser/__init__.py
collective/imagemaps/browser/configure.zcml
collective/imagemaps/browser/overrides/.gitkeep
collective/imagemaps/browser/static/.gitkeep
collective/imagemaps/locales/README.rst
collective/imagemaps/locales/__init__.py
collective/imagemaps/locales/collective.imagemaps.pot
collective/imagemaps/locales/update.py
collective/imagemaps/locales/update.sh
collective/imagemaps/locales/en/LC_MESSAGES/collective.imagemaps.po
collective/imagemaps/profiles/default/browserlayer.xml
collective/imagemaps/profiles/default/catalog.xml
collective/imagemaps/profiles/default/metadata.xml
collective/imagemaps/profiles/default/rolemap.xml
collective/imagemaps/profiles/default/registry/main.xml
collective/imagemaps/profiles/uninstall/browserlayer.xml
collective/imagemaps/tests/__init__.py
collective/imagemaps/tests/test_behavior_image_map.py
collective/imagemaps/tests/test_robot.py
collective/imagemaps/tests/test_setup.py
collective/imagemaps/tests/test_viewlet_image_map_viewlet.py
collective/imagemaps/tests/robot/test_example.robot
collective/imagemaps/viewlets/__init__.py
collective/imagemaps/viewlets/configure.zcml
collective/imagemaps/viewlets/image_map_viewlet.py
collective_imagemaps-2.0a1.dist-info/licenses/LICENSE.GPL
collective_imagemaps-2.0a1.dist-info/licenses/LICENSE.rst
collective_imagemaps-2.0a1.dist-info/METADATA
collective_imagemaps-2.0a1.dist-info/WHEEL
collective_imagemaps-2.0a1.dist-info/entry_points.txt
collective_imagemaps-2.0a1.dist-info/namespace_packages.txt
collective_imagemaps-2.0a1.dist-info/top_level.txt
collective_imagemaps-2.0a1.dist-info/RECORD
